{
  "configVersion": 1,
  "timestamp": 1763657297615,
  "index": "/exp-tracker/index.html",
  "assetGroups": [
    {
      "name": "app",
      "installMode": "prefetch",
      "updateMode": "prefetch",
      "cacheQueryOptions": {
        "ignoreVary": true
      },
      "urls": [
        "/exp-tracker/chunk-2VC2U6PB.js",
        "/exp-tracker/chunk-BLONM6LW.js",
        "/exp-tracker/chunk-BNKXWPD5.js",
        "/exp-tracker/chunk-DVM6R6AE.js",
        "/exp-tracker/chunk-EA55MFFL.js",
        "/exp-tracker/chunk-G2JDWZIQ.js",
        "/exp-tracker/chunk-GN4ZCS4F.js",
        "/exp-tracker/chunk-HQ2JUO3K.js",
        "/exp-tracker/chunk-JDYH5545.js",
        "/exp-tracker/chunk-L4WKIOFU.js",
        "/exp-tracker/chunk-MPW226X4.js",
        "/exp-tracker/chunk-NKEPFT7J.js",
        "/exp-tracker/chunk-ORAROT63.js",
        "/exp-tracker/chunk-PHPQO2QT.js",
        "/exp-tracker/chunk-PHWQ2XA3.js",
        "/exp-tracker/chunk-XS26AGT3.js",
        "/exp-tracker/chunk-Y3D5E434.js",
        "/exp-tracker/favicon.ico",
        "/exp-tracker/index.html",
        "/exp-tracker/main-TZLACBBO.js",
        "/exp-tracker/manifest.webmanifest",
        "/exp-tracker/scripts-TTWY4XDY.js",
        "/exp-tracker/styles-HR6D4WJL.css"
      ],
      "patterns": []
    },
    {
      "name": "assets",
      "installMode": "lazy",
      "updateMode": "prefetch",
      "cacheQueryOptions": {
        "ignoreVary": true
      },
      "urls": [
        "/exp-tracker/icons/icon-128x128.png",
        "/exp-tracker/icons/icon-144x144.png",
        "/exp-tracker/icons/icon-152x152.png",
        "/exp-tracker/icons/icon-192x192.png",
        "/exp-tracker/icons/icon-384x384.png",
        "/exp-tracker/icons/icon-512x512.png",
        "/exp-tracker/icons/icon-72x72.png",
        "/exp-tracker/icons/icon-96x96.png",
        "/exp-tracker/media/bootstrap-icons-CVBWLLHT.woff2",
        "/exp-tracker/media/bootstrap-icons-VQNJTM6Q.woff"
      ],
      "patterns": []
    }
  ],
  "dataGroups": [],
  "hashTable": {
    "/exp-tracker/chunk-2VC2U6PB.js": "1dbca823f439d93e31b73873c4981ba48e690b97",
    "/exp-tracker/chunk-BLONM6LW.js": "62ed1d7236293fa7bcd21bd6b15ef341da13a01e",
    "/exp-tracker/chunk-BNKXWPD5.js": "822324a37c7d0939b07108c645f0077587aee6cc",
    "/exp-tracker/chunk-DVM6R6AE.js": "ca66a84043398eee870193d07d3a18a83a151d80",
    "/exp-tracker/chunk-EA55MFFL.js": "03df76f98882ad67cdb7ce734a8a7ea726fb67d5",
    "/exp-tracker/chunk-G2JDWZIQ.js": "0ca16ebe5ead8e5b8c5f34e62ae1324f1a89a597",
    "/exp-tracker/chunk-GN4ZCS4F.js": "2b5b5c4741caf2c29c096ec6e9bc9dd179fe33f2",
    "/exp-tracker/chunk-HQ2JUO3K.js": "e5d5c09381051c029b09a004573145891e9d4c7c",
    "/exp-tracker/chunk-JDYH5545.js": "6e382d55b5251f65dac34e0095f2416732d3066d",
    "/exp-tracker/chunk-L4WKIOFU.js": "cfec2d921466d2708751fd500f27f13fcd94c95a",
    "/exp-tracker/chunk-MPW226X4.js": "756ab0b2ef678bb06e05a1b3c126c282f16deea1",
    "/exp-tracker/chunk-NKEPFT7J.js": "ca4082cfa707852b0f24585e29bb00c028bf173f",
    "/exp-tracker/chunk-ORAROT63.js": "d609d4f31e5fc71795e2eddbac33d50ee5dc1e87",
    "/exp-tracker/chunk-PHPQO2QT.js": "482d52c429521d3724ce24c92b6aee22d1183412",
    "/exp-tracker/chunk-PHWQ2XA3.js": "d65d43b4a3cd42fc628afc5283259bf33e502213",
    "/exp-tracker/chunk-XS26AGT3.js": "2a1e4748ce23fcb612bdf422dfe7434882137362",
    "/exp-tracker/chunk-Y3D5E434.js": "66326497dc253cfaf9fb47523089bc53d133a723",
    "/exp-tracker/favicon.ico": "9c39f434fe1261f68c5e3eefdf734630d99c5670",
    "/exp-tracker/icons/icon-128x128.png": "f912963bdc6d5a38d8f1dd0afbaab2ce8d657acb",
    "/exp-tracker/icons/icon-144x144.png": "b155fd5f2fd5d2ea7760721063003c4cd95fd783",
    "/exp-tracker/icons/icon-152x152.png": "eae6e0f0c8afb8aaae339e2a569b43e9238e5e6c",
    "/exp-tracker/icons/icon-192x192.png": "15c4180454633880d98674aa7394656196c91584",
    "/exp-tracker/icons/icon-384x384.png": "94a915751ef6c9282df9aea405ad679230631814",
    "/exp-tracker/icons/icon-512x512.png": "1de182f76f7329dfa8f9fcdd1fdcdd695bea6a99",
    "/exp-tracker/icons/icon-72x72.png": "aa88a6096bd973be7f6d7a5489bfa6bc2463f8c4",
    "/exp-tracker/icons/icon-96x96.png": "7fb8f59c30ce2ff12c700321a0b39e14b3dc8f95",
    "/exp-tracker/index.html": "e95e759e4db59a180a7af6fff6695dd3b59c5dcf",
    "/exp-tracker/main-TZLACBBO.js": "35332902a07ca5bd56e52653583eb09908d1647b",
    "/exp-tracker/manifest.webmanifest": "befff9e8dcd5b3681a82522d2799c7c6338c75f4",
    "/exp-tracker/media/bootstrap-icons-CVBWLLHT.woff2": "b441fcff939e24fa0906a37b7788788b9fddbb68",
    "/exp-tracker/media/bootstrap-icons-VQNJTM6Q.woff": "762010c79b4a05e1131fc8fb3b1aeff324d8033f",
    "/exp-tracker/scripts-TTWY4XDY.js": "59aa489af6324127a3d773836250da08639d4b26",
    "/exp-tracker/styles-HR6D4WJL.css": "d374cc75d6f482d20271f7a8c80ccc111c8e48bc"
  },
  "navigationUrls": [
    {
      "positive": true,
      "regex": "^\\/.*$"
    },
    {
      "positive": false,
      "regex": "^\\/(?:.+\\/)?[^/]*\\.[^/]*$"
    },
    {
      "positive": false,
      "regex": "^\\/(?:.+\\/)?[^/]*__[^/]*$"
    },
    {
      "positive": false,
      "regex": "^\\/(?:.+\\/)?[^/]*__[^/]*\\/.*$"
    }
  ],
  "navigationRequestStrategy": "performance"
}